{
    "Subject": "201104",
    "RatStrain": "Sprague Dawley",
    "RatSex": "male",
    "AnesthesiaMaintenance": "medetomidine",
    "TaskName": "sensory-stimulation",
    "Paradigm": {
        "SensorySystem": "forepaw",
        "Type": "electric",
        "Onsets": "21, 63, 105, 147, 189, 231, 273",
        "Duration": "21, 21, 21, 21, 21, 21, 21"
    },
    "MRIVendor": "Varian/Agilent",
    "MagneticFieldStrength": 14.0,
    "EchoTime": 0.0167,
    "RepetitionTime": 1.5,
    "Sequence": "GE-EPI"
}